{
  "date": "2026-04-27",
  "strategy": "v1.3",
  "portfolio_before": {
    "cash": 85000.0,
    "total_value": 275060.0,
    "position_count": 2
  },
  "actions": [
    {
      "symbol": "600346.SSE",
      "name": "600346",
      "action": "BUY",
      "shares": 1600,
      "ref_price": 22.09,
      "estimated_amount": 35344.0,
      "current_pnl_pct": 0.0,
      "reason": "new_entry",
      "signal_prob": 0.8547597527503967,
      "signal_rank": 1,
      "estimated_cost": 35344.0
    },
    {
      "symbol": "002384.SZSE",
      "name": "002384",
      "action": "BUY",
      "shares": 100,
      "ref_price": 186.73,
      "estimated_amount": 18673.0,
      "current_pnl_pct": 0.0,
      "reason": "new_entry",
      "signal_prob": 0.5800932049751282,
      "signal_rank": 2,
      "estimated_cost": 18673.0
    },
    {
      "symbol": "600482.SSE",
      "name": "600482",
      "action": "BUY",
      "shares": 900,
      "ref_price": 38.57,
      "estimated_amount": 34713.0,
      "current_pnl_pct": 0.0,
      "reason": "new_entry",
      "signal_prob": 0.5363360047340393,
      "signal_rank": 5,
      "estimated_cost": 34713.0
    },
    {
      "symbol": "002463.SZSE",
      "name": "002463",
      "action": "BUY",
      "shares": 300,
      "ref_price": 102.57,
      "estimated_amount": 30771.0,
      "current_pnl_pct": 0.0,
      "reason": "new_entry",
      "signal_prob": 0.5306687355041504,
      "signal_rank": 6,
      "estimated_cost": 30771.0
    },
    {
      "symbol": "002938.SZSE",
      "name": "002938",
      "action": "BUY",
      "shares": 400,
      "ref_price": 72.05,
      "estimated_amount": 28820.0,
      "current_pnl_pct": 0.0,
      "reason": "new_entry",
      "signal_prob": 0.5300406813621521,
      "signal_rank": 7,
      "estimated_cost": 28820.0
    },
    {
      "symbol": "688126.SSE",
      "name": "688126",
      "action": "BUY",
      "shares": 1700,
      "ref_price": 20.61,
      "estimated_amount": 35037.0,
      "current_pnl_pct": 0.0,
      "reason": "new_entry",
      "signal_prob": 0.5260984301567078,
      "signal_rank": 8,
      "estimated_cost": 35037.0
    },
    {
      "symbol": "300394.SZSE",
      "name": "天孚通信",
      "action": "SELL",
      "shares": 200,
      "ref_price": 307.5,
      "estimated_amount": 61500.0,
      "current_pnl_pct": 1115.42,
      "reason": "rebalance_out",
      "signal_prob": 0.5210166573524475,
      "signal_rank": 9,
      "estimated_proceeds": 61500.0
    },
    {
      "symbol": "600519.SSE",
      "name": "贵州茅台",
      "action": "SELL",
      "shares": 100,
      "ref_price": 1384.79,
      "estimated_amount": 138479.0,
      "current_pnl_pct": -25.15,
      "reason": "rebalance_out",
      "signal_prob": 0.07500652223825455,
      "signal_rank": 249,
      "estimated_proceeds": 138479.0
    }
  ],
  "summary": {
    "buys": 6,
    "sells": 2,
    "holds": 0,
    "estimated_turnover": 383337.0
  },
  "model_info": {
    "train_cutoff": "cached",
    "signal_date": "2026-04-27",
    "signal_count": 279
  }
}